leaderboarddata/__init__.py
leaderboarddata/app.py
leaderboarddata-0.0.15.dist-info/METADATA
leaderboarddata-0.0.15.dist-info/RECORD
leaderboarddata-0.0.15.dist-info/WHEEL
leaderboarddata-0.0.15.dist-info/top_level.txt
