Metadata-Version: 2.1
Name: leaderboarddata
Version: 0.0.15
Summary: Back end service for SC2 ladder ranking leaderboard
Home-page: https://github.com/frugs/allin-data
Author: Hugo Wainwright
Author-email: wainwrighthugo@gmail.com
License: UNKNOWN
Keywords: sc2,MMR
Platform: UNKNOWN
Requires-Dist: requests-toolbelt (>=0.8.0)
Requires-Dist: sc2gamedata
Requires-Dist: retryfallback
Requires-Dist: flask
Requires-Dist: google-cloud-datastore
Requires-Dist: firebase-admin
